pbspark/__init__.py
pbspark/_proto.py
pbspark/_timestamp.py
pbspark/_version.py
pbspark-0.9.0.dist-info/LICENSE.txt
pbspark-0.9.0.dist-info/METADATA
pbspark-0.9.0.dist-info/WHEEL
pbspark-0.9.0.dist-info/RECORD
