Metadata-Version: 2.1
Name: pbspark
Version: 0.9.0
Summary: Convert between protobuf messages and pyspark dataframes
Home-page: https://github.com/crflynn/pbspark
License: MIT
Keywords: spark,protobuf,pyspark
Author: flynn
Author-email: crf204@gmail.com
Requires-Python: >=3.7,<4.0
Classifier: Development Status :: 4 - Beta
Classifier: License :: OSI Approved :: MIT License
Classifier: Programming Language :: Python
Classifier: Programming Language :: Python :: 3
Classifier: Programming Language :: Python :: 3.7
Classifier: Programming Language :: Python :: 3.8
Classifier: Programming Language :: Python :: 3.9
Classifier: Programming Language :: Python :: 3.10
Classifier: Programming Language :: Python :: 3.11
Classifier: Topic :: Database
Requires-Dist: protobuf (>=3.20.0)
Requires-Dist: pyspark (>=3.1.1)
Project-URL: Documentation, https://github.com/crflynn/pbspark
Project-URL: Repository, https://github.com/crflynn/pbspark
